[{"headline": "Startup Head Count Shrank for the First Time in Years, Carta Says", "article_time": "7:39 PM ET", "year": 2024, "month": 3, "day": 12, "keyword": "Pro VC Industry News", "link": "https://www.wsj.com/articles/startup-head-count-shrank-for-the-first-time-in-years-carta-says-69384f56", "scraped_at": "2024-10-26 22:25:28", "scanned_status": 0}, {"headline": "House Democrats Try to Bypass Speaker Johnson to Force Vote on Ukraine Aid", "article_time": "7:11 PM ET", "year": 2024, "month": 3, "day": 12, "keyword": "Politics", "link": "https://www.wsj.com/politics/policy/house-democrats-try-to-bypass-speaker-johnson-to-force-vote-on-ukraine-aid-5e33753f", "scraped_at": "2024-10-26 22:25:28", "scanned_status": 0}, {"headline": "Can Wegovy and Ozempic Help America\u2019s Obesity Problem?", "article_time": "6:42 PM ET", "year": 2024, "month": 3, "day": 12, "keyword": "Future View", "link": "https://www.wsj.com/articles/can-wegovy-and-ozempic-help-americas-obesity-problem-e1fb1f6b", "scraped_at": "2024-10-26 22:25:28", "scanned_status": 0}, {"headline": "Biden Shrinks the U.S. Military", "article_time": "6:33 PM ET", "year": 2024, "month": 3, "day": 12, "keyword": "Review & Outlook", "link": "https://www.wsj.com/articles/biden-defense-budget-pentagon-u-s-military-china-russia-israel-ukraine-ba7fd46b", "scraped_at": "2024-10-26 22:25:28", "scanned_status": 0}, {"headline": "A Joint-Employer Legal Smackdown", "article_time": "6:32 PM ET", "year": 2024, "month": 3, "day": 12, "keyword": "Review & Outlook", "link": "https://www.wsj.com/articles/national-labor-relations-board-joint-employer-rule-judge-john-campbell-barker-business-labor-07f2f8a5", "scraped_at": "2024-10-26 22:25:28", "scanned_status": 0}, {"headline": "Hold the Inflation Champagne", "article_time": "6:28 PM ET", "year": 2024, "month": 3, "day": 12, "keyword": "Review & Outlook", "link": "https://www.wsj.com/articles/prices-accelerate-cpi-federal-reserve-interest-rates-economy-84ed53e8", "scraped_at": "2024-10-26 22:25:28", "scanned_status": 0}, {"headline": "Robert Hur and the Hacks", "article_time": "6:27 PM ET", "year": 2024, "month": 3, "day": 12, "keyword": "Review & Outlook", "link": "https://www.wsj.com/articles/robert-hur-house-judiciary-testimony-joe-biden-classified-documents-b7e5f155", "scraped_at": "2024-10-26 22:25:28", "scanned_status": 0}, {"headline": "Israel and Hezbollah Exchange Fire as Tensions Flare", "article_time": "6:20 PM ET", "year": 2024, "month": 3, "day": 12, "keyword": "Middle East", "link": "https://www.wsj.com/world/middle-east/israel-and-hezbollah-exchange-fire-as-tensions-flare-on-lebanon-border-5b3e3f2c", "scraped_at": "2024-10-26 22:25:28", "scanned_status": 0}, {"headline": "Special Counsel\u2019s Testimony on Biden Report Angers Both Sides", "article_time": "6:16 PM ET", "year": 2024, "month": 3, "day": 12, "keyword": "Politics", "link": "https://www.wsj.com/politics/special-counsels-testimony-on-biden-report-angers-both-sides-0cf28ca0", "scraped_at": "2024-10-26 22:25:28", "scanned_status": 0}, {"headline": "Trump and Ukraine", "article_time": "6:01 PM ET", "year": 2024, "month": 3, "day": 12, "keyword": "Business World", "link": "https://www.wsj.com/articles/trump-and-ukraine-dont-listen-to-mainstream-media-predictions-on-second-term-0a7589cd", "scraped_at": "2024-10-26 22:25:28", "scanned_status": 0}, {"headline": "Activist Investor Land & Buildings Urges Office Owner to Liquidate", "article_time": "6:00 PM ET", "year": 2024, "month": 3, "day": 12, "keyword": "N/A", "link": "https://www.wsj.com/real-estate/commercial/activist-investor-land-buildings-urges-office-owner-to-liquidate-5eb9f023", "scraped_at": "2024-10-26 22:25:28", "scanned_status": 0}, {"headline": "Online Harms Act: Crime and Punishment, Not in That Order", "article_time": "5:59 PM ET", "year": 2024, "month": 3, "day": 12, "keyword": "Commentary", "link": "https://www.wsj.com/articles/crime-and-punishment-not-in-that-order-canada-hate-speech-f618e339", "scraped_at": "2024-10-26 22:25:28", "scanned_status": 0}, {"headline": "Mansour Abbas Is an Arab and a Proud Israeli", "article_time": "5:56 PM ET", "year": 2024, "month": 3, "day": 12, "keyword": "Commentary", "link": "https://www.wsj.com/articles/mansour-abbas-is-an-arab-and-a-proud-israeli-mideast-october-7-b4224ca6", "scraped_at": "2024-10-26 22:25:28", "scanned_status": 0}, {"headline": "The SAT\u2019s Comeback Is Good News for Minority Students", "article_time": "5:52 PM ET", "year": 2024, "month": 3, "day": 12, "keyword": "Upward Mobility", "link": "https://www.wsj.com/articles/the-sats-comeback-is-good-news-for-minority-students-standardized-tests-bbdbe61e", "scraped_at": "2024-10-26 22:25:28", "scanned_status": 0}, {"headline": "Council That Would Rule Haiti Must Navigate Gangs, Other Powerful Forces", "article_time": "5:42 PM ET", "year": 2024, "month": 3, "day": 12, "keyword": "Latin America", "link": "https://www.wsj.com/world/americas/haitian-prime-minister-arielhenry-agrees-to-resign-bb0377fd", "scraped_at": "2024-10-26 22:25:28", "scanned_status": 0}, {"headline": "\u2018Deeper Well\u2019 by Kacey Musgraves Review: A Quiet Conversation", "article_time": "5:33 PM ET", "year": 2024, "month": 3, "day": 12, "keyword": "Music Review", "link": "https://www.wsj.com/arts-culture/music/deeper-well-by-kacey-musgraves-review-a-quiet-conversation-f1f25c2f", "scraped_at": "2024-10-26 22:25:28", "scanned_status": 0}, {"headline": "\u2018Manhunt\u2019 Review: Pursuing John Wilkes Booth on Apple TV+", "article_time": "5:32 PM ET", "year": 2024, "month": 3, "day": 12, "keyword": "Television Review", "link": "https://www.wsj.com/arts-culture/television/manhunt-review-pursuing-john-wilkes-booth-on-apple-tv-05e644d2", "scraped_at": "2024-10-26 22:25:28", "scanned_status": 0}, {"headline": "U.S. Sending $300 Million in Ammunition, Weapons to Ukraine", "article_time": "5:09 PM ET", "year": 2024, "month": 3, "day": 12, "keyword": "National Security", "link": "https://www.wsj.com/politics/national-security/u-s-sending-300-million-in-ammunition-weapons-to-ukraine-07402244", "scraped_at": "2024-10-26 22:25:28", "scanned_status": 0}, {"headline": "S&P 500 Hits New Record After Hot Inflation Data", "article_time": "5:03 PM ET", "year": 2024, "month": 3, "day": 12, "keyword": "U.S. Markets", "link": "https://www.wsj.com/finance/stocks/global-stocks-markets-dow-news-03-12-2024-2daf1bb0", "scraped_at": "2024-10-26 22:25:28", "scanned_status": 0}, {"headline": "IRS Tax-Filing Pilot Opens Wide, With Aim of 100,000 First-Year Users", "article_time": "4:59 PM ET", "year": 2024, "month": 3, "day": 12, "keyword": "U.S.", "link": "https://www.wsj.com/personal-finance/taxes/irs-tax-filing-pilot-opens-wide-with-aim-of-100-000-first-year-users-01110f0e", "scraped_at": "2024-10-26 22:25:28", "scanned_status": 0}, {"headline": "U.S. Bank Regulators Weigh New Operational Resilience Requirements", "article_time": "4:59 PM ET", "year": 2024, "month": 3, "day": 12, "keyword": "Risk & Compliance Journal", "link": "https://www.wsj.com/articles/u-s-bank-regulators-weigh-new-operational-resilience-requirements-a5ef6d04", "scraped_at": "2024-10-26 22:25:28", "scanned_status": 0}, {"headline": "Inflation Picks Up to 3.2%, Slightly Hotter Than Expected", "article_time": "4:26 PM ET", "year": 2024, "month": 3, "day": 12, "keyword": "U.S. Economy", "link": "https://www.wsj.com/economy/inflation-february-cpi-report-interest-rate-b827c0e7", "scraped_at": "2024-10-26 22:25:28", "scanned_status": 0}, {"headline": "Airlines Are Cutting Flight Schedules as Boeing Delivers Fewer Jets", "article_time": "4:25 PM ET", "year": 2024, "month": 3, "day": 12, "keyword": "Business", "link": "https://www.wsj.com/business/airlines/southwest-airlines-is-reevaluating-2024-guidance-due-to-boeing-challenges-c0d27c62", "scraped_at": "2024-10-26 22:25:28", "scanned_status": 0}, {"headline": "Do You Have Painful \u2018Tech Neck?\u2019 This Expert-Approved Gadget Might Help", "article_time": "4:15 PM ET", "year": 2024, "month": 3, "day": 12, "keyword": "Gear & Gadgets", "link": "https://www.wsj.com/tech/personal-tech/therabody-powerdot-2-tech-neck-pain-gadget-might-help-cd454931", "scraped_at": "2024-10-26 22:25:28", "scanned_status": 0}, {"headline": "Saints and the Bible Tell the Truth About Hell", "article_time": "4:13 PM ET", "year": 2024, "month": 3, "day": 12, "keyword": "Letters", "link": "https://www.wsj.com/articles/saints-and-the-bible-tell-the-truth-about-hell-faustina-fatima-lazarus-ff6d072c", "scraped_at": "2024-10-26 22:25:28", "scanned_status": 0}, {"headline": "Targeting Tariffs on Chinese Cars Isn\u2019t Easy", "article_time": "4:11 PM ET", "year": 2024, "month": 3, "day": 12, "keyword": "Letters", "link": "https://www.wsj.com/articles/targeting-tariffs-on-chinese-cars-isnt-easy-mexico-electric-1316dbaf", "scraped_at": "2024-10-26 22:25:28", "scanned_status": 0}, {"headline": "Lower Barriers for Weight-Loss Drug Coverage ", "article_time": "4:09 PM ET", "year": 2024, "month": 3, "day": 12, "keyword": "Letters", "link": "https://www.wsj.com/articles/lower-barriers-for-weight-loss-drug-coverage-ozempic-wegovy-9fb8b68d", "scraped_at": "2024-10-26 22:25:28", "scanned_status": 0}, {"headline": "Who Really Grew the Navy?", "article_time": "4:07 PM ET", "year": 2024, "month": 3, "day": 12, "keyword": "Letters", "link": "https://www.wsj.com/articles/who-really-grew-the-navy-trump-bush-ships-ford-5f21de01", "scraped_at": "2024-10-26 22:25:28", "scanned_status": 0}, {"headline": "Evangelicals and Trump Share the Same Concerns", "article_time": "4:05 PM ET", "year": 2024, "month": 3, "day": 12, "keyword": "Letters", "link": "https://www.wsj.com/articles/evangelicals-and-trump-share-the-same-concerns-religious-supreme-court-c9f3c9f8", "scraped_at": "2024-10-26 22:25:28", "scanned_status": 0}, {"headline": "Cut Down to Size (Wednesday Crossword, March 13)", "article_time": "4:01 PM ET", "year": 2024, "month": 3, "day": 12, "keyword": "Crossword", "link": "https://www.wsj.com/articles/cut-down-to-size-wednesday-crossword-march-13-e750e771", "scraped_at": "2024-10-26 22:25:28", "scanned_status": 0}, {"headline": "U.S. Lawmakers Push for Deep-Sea Mining Funding in New Bill", "article_time": "4:00 PM ET", "year": 2024, "month": 3, "day": 12, "keyword": "N/A", "link": "https://www.wsj.com/articles/u-s-lawmakers-to-push-for-deep-sea-mining-funding-in-new-bill-cc020f7d", "scraped_at": "2024-10-26 22:25:28", "scanned_status": 0}, {"headline": "How TikTok Was Blindsided by U.S. Bill That Could Ban It", "article_time": "3:42 PM ET", "year": 2024, "month": 3, "day": 12, "keyword": "N/A", "link": "https://www.wsj.com/tech/how-tiktok-was-blindsided-by-a-u-s-bill-that-could-ban-it-7201ac8b", "scraped_at": "2024-10-26 22:25:28", "scanned_status": 0}, {"headline": "China Raises Fines on Mintz Due-Diligence Firm", "article_time": "3:18 PM ET", "year": 2024, "month": 3, "day": 12, "keyword": "Asia", "link": "https://www.wsj.com/world/china/china-raises-fines-on-mintz-due-diligence-firm-c7486aeb", "scraped_at": "2024-10-26 22:25:28", "scanned_status": 0}, {"headline": "Inside Biden\u2019s Special Counsel Interview: Riffs, Jokes and the Occasional Flub", "article_time": "2:45 PM ET", "year": 2024, "month": 3, "day": 12, "keyword": "Election 2024", "link": "https://www.wsj.com/politics/inside-bidens-special-counsel-interview-riffs-jokes-and-the-occasional-flub-99fc04d0", "scraped_at": "2024-10-26 22:25:28", "scanned_status": 0}, {"headline": "First Boat Carrying Aid for Starving Gazans Departs Cyprus", "article_time": "2:43 PM ET", "year": 2024, "month": 3, "day": 12, "keyword": "Middle East", "link": "https://www.wsj.com/world/middle-east/first-boat-carrying-aid-for-starving-gazans-departs-cyprus-b5361616", "scraped_at": "2024-10-26 22:25:28", "scanned_status": 0}, {"headline": "Where the Cheering Stopped", "article_time": "2:03 PM ET", "year": 2024, "month": 3, "day": 12, "keyword": "Best of the Web", "link": "https://www.wsj.com/articles/where-the-cheering-stopped-5889845f", "scraped_at": "2024-10-26 22:25:28", "scanned_status": 0}, {"headline": "The NIH Sacrifices Scientific Rigor for DEI", "article_time": "1:41 PM ET", "year": 2024, "month": 3, "day": 12, "keyword": "Commentary", "link": "https://www.wsj.com/articles/the-nih-sacrifices-scientific-rigor-for-dei-f828a6c7", "scraped_at": "2024-10-26 22:25:28", "scanned_status": 0}, {"headline": "The Dire Cost of \u2018Peace\u2019 in Ukraine", "article_time": "1:37 PM ET", "year": 2024, "month": 3, "day": 12, "keyword": "Politics & Ideas", "link": "https://www.wsj.com/articles/the-dire-cost-of-peace-in-ukraine-trump-war-russia-military-aid-c186b23c", "scraped_at": "2024-10-26 22:25:28", "scanned_status": 0}, {"headline": "Tesla, Ford Receive \u2018Poor\u2019 Grades in Study of Driver-Assist Technology", "article_time": "1:14 PM ET", "year": 2024, "month": 3, "day": 12, "keyword": "Autos Industry", "link": "https://www.wsj.com/business/autos/tesla-ford-receive-poor-grades-in-study-of-driver-assist-technology-adab59e0", "scraped_at": "2024-10-26 22:25:28", "scanned_status": 0}, {"headline": "How \u2018Girls5Eva\u2019 Star Busy Philipps Turned Being Weird Into a Career", "article_time": "1:06 PM ET", "year": 2024, "month": 3, "day": 12, "keyword": "House Call", "link": "https://www.wsj.com/real-estate/busy-philipps-girls5eva-a23ca6e4", "scraped_at": "2024-10-26 22:25:28", "scanned_status": 0}, {"headline": "\u2018Europeras 3 & 4\u2019 Review: John Cage\u2019s Controlled Chaos", "article_time": "1:06 PM ET", "year": 2024, "month": 3, "day": 12, "keyword": "Opera Review", "link": "https://www.wsj.com/arts-culture/music/europeras-3-4-review-john-cage-detroit-opera-yuval-sharon-f59ed0a6", "scraped_at": "2024-10-26 22:25:28", "scanned_status": 0}, {"headline": "The Tournament That Became the Biggest Loser in Golf\u2019s Civil War", "article_time": "12:58 PM ET", "year": 2024, "month": 3, "day": 12, "keyword": "Golf", "link": "https://www.wsj.com/sports/golf/players-championship-2024-field-pga-tour-liv-golf-8288a279", "scraped_at": "2024-10-26 22:25:28", "scanned_status": 0}, {"headline": "Crypto Gets Blamed for a Real-Life Currency Crisis", "article_time": "12:25 PM ET", "year": 2024, "month": 3, "day": 12, "keyword": "N/A", "link": "https://www.wsj.com/finance/currencies/crypto-gets-blamed-for-a-real-life-currency-crisis-e3e3b343", "scraped_at": "2024-10-26 22:25:28", "scanned_status": 0}, {"headline": "Alaska Air Anticipates Better-Than-Expected First Quarter Despite Boeing Grounding", "article_time": "12:21 PM ET", "year": 2024, "month": 3, "day": 12, "keyword": "Business", "link": "https://www.wsj.com/business/earnings/alaska-airlines-returns-fleet-to-service-after-boeing-grounding-304d503b", "scraped_at": "2024-10-26 22:25:28", "scanned_status": 0}, {"headline": "\u2018To Make a Killing\u2019 Review: The Wheat King\u2019s Lost Harvest", "article_time": "12:14 PM ET", "year": 2024, "month": 3, "day": 12, "keyword": "Bookshelf", "link": "https://www.wsj.com/arts-culture/books/to-make-a-killing-review-the-wheat-kings-lost-harvest-8877bdc9", "scraped_at": "2024-10-26 22:25:28", "scanned_status": 0}, {"headline": "Ukrainian Drone Strikes Disrupt Russian Oil Industry", "article_time": "12:14 PM ET", "year": 2024, "month": 3, "day": 12, "keyword": "World", "link": "https://www.wsj.com/world/europe/ukrainian-drone-strikes-disrupt-russian-oil-industry-84436092", "scraped_at": "2024-10-26 22:25:28", "scanned_status": 0}, {"headline": "3M Names New CEO Amid PFAS Battles, Health Spinoff", "article_time": "12:02 PM ET", "year": 2024, "month": 3, "day": 12, "keyword": "Business", "link": "https://www.wsj.com/tech/3m-names-william-brown-chief-executive-c3f34cb7", "scraped_at": "2024-10-26 22:25:28", "scanned_status": 0}, {"headline": "A Closer Look", "article_time": "11:47 AM ET", "year": 2024, "month": 3, "day": 12, "keyword": "Slideshow", "link": "https://www.wsj.com/articles/a-closer-look-9c49110d", "scraped_at": "2024-10-26 22:25:28", "scanned_status": 0}, {"headline": "A Closer Look", "article_time": "11:46 AM ET", "year": 2024, "month": 3, "day": 12, "keyword": "Slideshow", "link": "https://www.wsj.com/articles/a-closer-look-c9a4176c", "scraped_at": "2024-10-26 22:25:28", "scanned_status": 0}, {"headline": "A Closer Look", "article_time": "11:44 AM ET", "year": 2024, "month": 3, "day": 12, "keyword": "Slideshow", "link": "https://www.wsj.com/articles/a-closer-look-cf387317", "scraped_at": "2024-10-26 22:25:28", "scanned_status": 0}]