[{"headline": "Iowans Fault DNC for Role in Caucus Debacle", "article_time": "7:18 PM ET", "year": 2020, "month": 12, "day": 12, "keyword": "Election 2020", "link": "https://www.wsj.com/articles/iowans-fault-democratic-national-committee-for-role-in-caucus-debacle-11607818737", "scraped_at": "2024-10-24 19:09:43", "scanned_status": 0}, {"headline": "Pfizer-BioNTech Shot Recommended for CDC Immunization Schedule", "article_time": "6:20 PM ET", "year": 2020, "month": 12, "day": 12, "keyword": "Health Policy", "link": "https://www.wsj.com/articles/pfizer-biontech-covid-19-vaccine-recommended-for-cdc-immunization-schedule-11607815223", "scraped_at": "2024-10-24 19:09:43", "scanned_status": 0}, {"headline": "Singer Charley Pride Dies at Age 86", "article_time": "6:13 PM ET", "year": 2020, "month": 12, "day": 12, "keyword": "Obituaries", "link": "https://www.wsj.com/articles/charley-pride-country-musics-first-black-star-dies-at-age-86-11607814223", "scraped_at": "2024-10-24 19:09:43", "scanned_status": 0}, {"headline": "Photos of the Week", "article_time": "5:45 PM ET", "year": 2020, "month": 12, "day": 12, "keyword": "World", "link": "https://www.wsj.com/articles/photos-of-the-week-airbnb-stock-price-soars-u-k-begins-rollout-of-pfizers-covid-19-vaccine-hanukkah-celebrations-begin-and-more-11607808601", "scraped_at": "2024-10-24 19:09:43", "scanned_status": 0}, {"headline": "How the Covid Pandemic Will Change Online Dating", "article_time": "4:00 PM ET", "year": 2020, "month": 12, "day": 12, "keyword": "Journal Reports: Year in Review", "link": "https://www.wsj.com/articles/how-the-covid-pandemic-will-change-online-dating-11607806800", "scraped_at": "2024-10-24 19:09:43", "scanned_status": 0}, {"headline": "Affirm Delays Its IPO ", "article_time": "3:11 PM ET", "year": 2020, "month": 12, "day": 12, "keyword": "N/A", "link": "https://www.wsj.com/articles/affirm-postpones-initial-public-offering-sources-say-11607801619", "scraped_at": "2024-10-24 19:09:43", "scanned_status": 0}, {"headline": "Marcus Samuelsson on Restaurants in 2020: Fear, Change\u2014and Hope", "article_time": "3:00 PM ET", "year": 2020, "month": 12, "day": 12, "keyword": "Journal Reports: Year in Review", "link": "https://www.wsj.com/articles/marcus-samuelsson-on-restaurants-in-2020-fear-changeand-hope-11607803201", "scraped_at": "2024-10-24 19:09:43", "scanned_status": 0}, {"headline": "AstraZeneca\u2019s Alexion Splurge Could Attract a Crowd ", "article_time": "1:28 PM ET", "year": 2020, "month": 12, "day": 12, "keyword": "Heard on the Street", "link": "https://www.wsj.com/articles/astrazenecas-alexion-splurge-could-attract-a-crowd-11607797721", "scraped_at": "2024-10-24 19:09:43", "scanned_status": 0}, {"headline": "What\u2014and How\u2014People Were Reading During Covid-19", "article_time": "1:00 PM ET", "year": 2020, "month": 12, "day": 12, "keyword": "Journal Reports: Year in Review", "link": "https://www.wsj.com/articles/whatand-howpeople-were-reading-during-covid-19-11607796000", "scraped_at": "2024-10-24 19:09:43", "scanned_status": 0}, {"headline": "NFL Ratings Drop Leaves Networks Scrambling to Make Advertisers Whole", "article_time": "12:48 PM ET", "year": 2020, "month": 12, "day": 12, "keyword": "CMO Today", "link": "https://www.wsj.com/articles/nfl-ratings-drop-leaves-networks-scrambling-to-make-advertisers-whole-11607781600", "scraped_at": "2024-10-24 19:09:43", "scanned_status": 0}, {"headline": "AstraZeneca Agrees to Buy Alexion for $39 Billion ", "article_time": "12:27 PM ET", "year": 2020, "month": 12, "day": 12, "keyword": "Business", "link": "https://www.wsj.com/articles/astrazeneca-agrees-to-buy-alexion-for-39-billion-11607778687", "scraped_at": "2024-10-24 19:09:43", "scanned_status": 0}, {"headline": "The Best Television of 2020: Binge-Watching Our Way Through Quarantine", "article_time": "12:00 PM ET", "year": 2020, "month": 12, "day": 12, "keyword": "Television Review", "link": "https://www.wsj.com/articles/the-best-television-of-2020-binge-watching-our-way-through-quarantine-11607792400", "scraped_at": "2024-10-24 19:09:43", "scanned_status": 0}, {"headline": "The Year Wildfires in the West Spread Like the Plague", "article_time": "11:00 AM ET", "year": 2020, "month": 12, "day": 12, "keyword": "Journal Reports: Year in Review", "link": "https://www.wsj.com/articles/the-year-wildfires-in-the-west-spread-like-the-plague-11607788801", "scraped_at": "2024-10-24 19:09:43", "scanned_status": 0}, {"headline": "Jay Leno on How Driving Changed in 2020\u2014and How It Will Change Even More", "article_time": "11:00 AM ET", "year": 2020, "month": 12, "day": 12, "keyword": "Journal Reports: Year in Review", "link": "https://www.wsj.com/articles/jay-leno-on-how-driving-changed-in-2020and-how-it-will-change-even-more-11607788800", "scraped_at": "2024-10-24 19:09:43", "scanned_status": 0}, {"headline": "Trump Eyes Special Counsel for Election, Hunter Biden", "article_time": "10:21 AM ET", "year": 2020, "month": 12, "day": 12, "keyword": "N/A", "link": "https://www.wsj.com/articles/trump-pursues-appointing-special-counsel-to-probe-election-hunter-biden-11607744814", "scraped_at": "2024-10-24 19:09:43", "scanned_status": 0}, {"headline": "What the WSJ Management Top 250 Rankings Measure\u2014and How Well", "article_time": "10:13 AM ET", "year": 2020, "month": 12, "day": 12, "keyword": "Journal Reports: Leadership", "link": "https://www.wsj.com/articles/what-the-wsj-management-top-250-rankings-measureand-how-well-11607786018", "scraped_at": "2024-10-24 19:09:43", "scanned_status": 0}, {"headline": "Warning Signs in the Best-Managed Companies", "article_time": "10:12 AM ET", "year": 2020, "month": 12, "day": 12, "keyword": "Journal Reports: Leadership", "link": "https://www.wsj.com/articles/warning-signs-in-the-best-managed-companies-11607785916", "scraped_at": "2024-10-24 19:09:43", "scanned_status": 0}, {"headline": "What\u2019s New in the WSJ Management Top 250 Rankings for 2020", "article_time": "10:12 AM ET", "year": 2020, "month": 12, "day": 12, "keyword": "Journal Reports: Leadership", "link": "https://www.wsj.com/articles/whats-new-in-the-wsj-management-top-250-rankings-for-2020-11607785963", "scraped_at": "2024-10-24 19:09:43", "scanned_status": 0}, {"headline": "The Best-Managed Companies of 2020\u2014and How They Got That Way", "article_time": "10:10 AM ET", "year": 2020, "month": 12, "day": 12, "keyword": "Journal Reports: Leadership", "link": "https://www.wsj.com/articles/the-best-managed-companies-of-2020and-how-they-got-that-way-11607785803", "scraped_at": "2024-10-24 19:09:43", "scanned_status": 0}, {"headline": "Explore the Management Top 250", "article_time": "10:04 AM ET", "year": 2020, "month": 12, "day": 12, "keyword": "Journal Reports: Leadership", "link": "https://www.wsj.com/articles/explore-the-management-top-250-11607785450", "scraped_at": "2024-10-24 19:09:43", "scanned_status": 0}, {"headline": "Dividends Will Have Their Day Again ", "article_time": "10:03 AM ET", "year": 2020, "month": 12, "day": 12, "keyword": "Heard on the Street", "link": "https://www.wsj.com/articles/dividends-will-have-their-day-again-11607785380", "scraped_at": "2024-10-24 19:09:43", "scanned_status": 0}, {"headline": "Methodology for the Management Top 250 Company Rankings", "article_time": "10:01 AM ET", "year": 2020, "month": 12, "day": 12, "keyword": "Journal Reports: Leadership", "link": "https://www.wsj.com/articles/methodology-for-the-management-top-250-company-rankings-11607785307", "scraped_at": "2024-10-24 19:09:43", "scanned_status": 0}, {"headline": "Shutting Borders Helped Australia Contain Covid-19. Now Reopening Them Is Proving Difficult.", "article_time": "9:00 AM ET", "year": 2020, "month": 12, "day": 12, "keyword": "World", "link": "https://www.wsj.com/articles/shutting-borders-helped-australia-contain-covid-19-now-reopening-them-is-proving-difficult-11607781600", "scraped_at": "2024-10-24 19:09:43", "scanned_status": 0}, {"headline": "New York City Students Get Early Assist in Saving for College ", "article_time": "8:03 AM ET", "year": 2020, "month": 12, "day": 12, "keyword": "Schools", "link": "https://www.wsj.com/articles/new-york-city-students-get-early-assist-in-saving-for-college-11607778222", "scraped_at": "2024-10-24 19:09:43", "scanned_status": 0}, {"headline": "How 79-Year-Old Martha Stewart Stays Zoom-Ready", "article_time": "8:03 AM ET", "year": 2020, "month": 12, "day": 12, "keyword": "Off Brand", "link": "https://www.wsj.com/articles/how-79-year-old-martha-stewart-stays-zoom-ready-11607778222", "scraped_at": "2024-10-24 19:09:43", "scanned_status": 0}, {"headline": "\u2018Working Together: The Photographers of the Kamoinge Workshop\u2019 Review: A Black Community Too Long Forgotten ", "article_time": "7:00 AM ET", "year": 2020, "month": 12, "day": 12, "keyword": "Art Review", "link": "https://www.wsj.com/articles/working-together-the-photographers-of-the-kamoinge-workshop-review-a-black-community-too-long-forgotten-11607774401", "scraped_at": "2024-10-24 19:09:43", "scanned_status": 0}, {"headline": "Concerts for a Covid Christmas", "article_time": "7:00 AM ET", "year": 2020, "month": 12, "day": 12, "keyword": "Music Review", "link": "https://www.wsj.com/articles/concerts-for-a-covid-christmas-11607774400", "scraped_at": "2024-10-24 19:09:43", "scanned_status": 0}, {"headline": "For One Prized Italian Tradition, Covid-19 Deals Heartbreaking Blow", "article_time": "5:35 AM ET", "year": 2020, "month": 12, "day": 12, "keyword": "Europe", "link": "https://www.wsj.com/articles/for-one-prized-italian-tradition-covid-deals-a-heartbreaking-blow-11607769329", "scraped_at": "2024-10-24 19:09:43", "scanned_status": 0}, {"headline": "When the Robinhood Crowd Buys for the Long Haul ", "article_time": "5:30 AM ET", "year": 2020, "month": 12, "day": 12, "keyword": "Personal Finance", "link": "https://www.wsj.com/articles/when-the-robinhood-crowd-buys-for-the-long-haul-11607769001", "scraped_at": "2024-10-24 19:09:43", "scanned_status": 0}, {"headline": "Gargling Could Slow Covid-19 Spread, Mouthwash Makers Say ", "article_time": "5:30 AM ET", "year": 2020, "month": 12, "day": 12, "keyword": "Business", "link": "https://www.wsj.com/articles/gargling-could-slow-covid-19-spread-mouthwash-makers-say-11607769000", "scraped_at": "2024-10-24 19:09:43", "scanned_status": 0}, {"headline": "Supreme Court Rejects Texas Challenge to Biden\u2019s Victory", "article_time": "12:23 AM ET", "year": 2020, "month": 12, "day": 12, "keyword": "Election 2020", "link": "https://www.wsj.com/articles/trump-campaign-loses-wisconsin-election-lawsuit-11607713668", "scraped_at": "2024-10-24 19:09:43", "scanned_status": 0}, {"headline": "How Autism and Invention Are Connected ", "article_time": "12:01 AM ET", "year": 2020, "month": 12, "day": 12, "keyword": "Essay", "link": "https://www.wsj.com/articles/how-autism-and-invention-are-connected-11607749260", "scraped_at": "2024-10-24 19:09:43", "scanned_status": 0}, {"headline": "Pepper...and Salt", "article_time": "12:01 AM ET", "year": 2020, "month": 12, "day": 12, "keyword": "Pepper & Salt", "link": "https://www.wsj.com/articles/pepper-and-salt-11607722612", "scraped_at": "2024-10-24 19:09:43", "scanned_status": 0}, {"headline": "Intel Not Inside: How Mobile Chips Overtook the Semiconductor Giant", "article_time": "12:00 AM ET", "year": 2020, "month": 12, "day": 12, "keyword": "Keywords", "link": "https://www.wsj.com/articles/intel-not-inside-how-mobile-chips-overtook-the-semiconductor-giant-11607749203", "scraped_at": "2024-10-24 19:09:43", "scanned_status": 0}]