[{"headline": "What Is Greenwashing? Here Is What Investors Need to Know", "article_time": "8:00 PM ET", "year": 2020, "month": 11, "day": 9, "keyword": "Journal Reports: Funds/ETFs", "link": "https://www.wsj.com/articles/what-is-greenwashing-here-is-what-investors-need-to-know-11604881371", "scraped_at": "2024-10-24 18:58:25", "scanned_status": 0}, {"headline": "As Smart-Beta Funds Struggle, Here\u2019s What to Do Now", "article_time": "8:00 PM ET", "year": 2020, "month": 11, "day": 9, "keyword": "Journal Reports: Funds/ETFs", "link": "https://www.wsj.com/articles/as-smart-beta-funds-struggle-heres-what-to-do-now-11604881285", "scraped_at": "2024-10-24 18:58:25", "scanned_status": 0}, {"headline": "Turkey\u2019s Erdogan Shakes Up Economic Leadership", "article_time": "7:17 PM ET", "year": 2020, "month": 11, "day": 9, "keyword": "World", "link": "https://www.wsj.com/articles/turkish-finance-minister-berat-albayrak-steps-down-11604859438", "scraped_at": "2024-10-24 18:58:25", "scanned_status": 0}, {"headline": "New York Congressional Delegation to Be Most Diverse in State History", "article_time": "7:00 PM ET", "year": 2020, "month": 11, "day": 9, "keyword": "State Street", "link": "https://www.wsj.com/articles/new-yorks-congressional-delegation-to-be-most-diverse-in-state-history-11604880000", "scraped_at": "2024-10-24 18:58:25", "scanned_status": 0}]