[{"headline": "Herbalife CFO Looks to Change Investor Views After Years of Activist Pressure", "article_time": "9:30 AM ET", "year": 2021, "month": 2, "day": 25, "keyword": "CFO Journal", "link": "https://www.wsj.com/articles/herbalife-cfo-looks-to-change-investor-views-after-years-of-activist-pressure-11614263400", "scraped_at": "2024-10-24 20:25:31", "scanned_status": 0}, {"headline": "Durable-Goods Climbed 3.4% in January", "article_time": "9:11 AM ET", "year": 2021, "month": 2, "day": 25, "keyword": "Economic Data", "link": "https://www.wsj.com/articles/u-s-durable-goods-climbed-3-4-in-january-11614262261", "scraped_at": "2024-10-24 20:25:31", "scanned_status": 0}, {"headline": "GameStop, Koss, AMC: What to Watch When the Stock Market Opens Today", "article_time": "9:08 AM ET", "year": 2021, "month": 2, "day": 25, "keyword": "U.S. Markets", "link": "https://www.wsj.com/articles/gamestop-koss-amc-what-to-watch-when-the-stock-market-opens-today-11614254269", "scraped_at": "2024-10-24 20:25:31", "scanned_status": 0}, {"headline": "Some New Jersey Nursing Homes Will Resume Visitations ", "article_time": "9:02 AM ET", "year": 2021, "month": 2, "day": 25, "keyword": "Tri-State Area", "link": "https://www.wsj.com/articles/some-new-jersey-nursing-homes-will-resume-visitations-as-covid-19-cases-fall-11614208882", "scraped_at": "2024-10-24 20:25:31", "scanned_status": 0}, {"headline": "China Lets Yuan Rise Steadily, Pressuring Exporters ", "article_time": "9:01 AM ET", "year": 2021, "month": 2, "day": 25, "keyword": "China", "link": "https://www.wsj.com/articles/china-lets-yuan-rise-steadily-pressuring-exporters-11614261708", "scraped_at": "2024-10-24 20:25:31", "scanned_status": 0}, {"headline": "Washington, D.C., Police Fight a Rise in Carjackings and Blame Covid-19 ", "article_time": "9:00 AM ET", "year": 2021, "month": 2, "day": 25, "keyword": "U.S.", "link": "https://www.wsj.com/articles/washington-d-c-police-fight-a-rise-in-carjackings-and-blame-covid-19-11614261600", "scraped_at": "2024-10-24 20:25:31", "scanned_status": 0}, {"headline": "Facebook Ad Campaign Promotes Personalized Advertising ", "article_time": "9:00 AM ET", "year": 2021, "month": 2, "day": 25, "keyword": "CMO Today", "link": "https://www.wsj.com/articles/facebook-ad-campaign-promotes-personalized-advertising-11614261617", "scraped_at": "2024-10-24 20:25:31", "scanned_status": 0}, {"headline": "The NBA\u2019s Top Shooter Is Named Curry. No, Not That One.", "article_time": "9:00 AM ET", "year": 2021, "month": 2, "day": 25, "keyword": "NBA", "link": "https://www.wsj.com/articles/seth-curry-philadelphia-76ers-steph-curry-11614234577", "scraped_at": "2024-10-24 20:25:31", "scanned_status": 0}, {"headline": "Was 'Punky Brewster'\u2019s Soleil Moon Frye the Original Influencer?", "article_time": "9:00 AM ET", "year": 2021, "month": 2, "day": 25, "keyword": "Magazine - Culture", "link": "https://www.wsj.com/articles/punky-brewster-soleil-moon-frye-90s-kid-documentary-hulu-11614261609", "scraped_at": "2024-10-24 20:25:31", "scanned_status": 0}, {"headline": "New Mail Trucks Are Finally Coming, but Don\u2019t Expect All Electric Vehicles ", "article_time": "8:44 AM ET", "year": 2021, "month": 2, "day": 25, "keyword": "U.S.", "link": "https://www.wsj.com/articles/new-mail-trucks-are-finally-coming-but-dont-expect-all-electric-vehicles-11614260671", "scraped_at": "2024-10-24 20:25:31", "scanned_status": 0}, {"headline": "Eve Hewson on Catfishing Strangers and Her New Starring Roles", "article_time": "8:37 AM ET", "year": 2021, "month": 2, "day": 25, "keyword": "Magazine - Culture", "link": "https://www.wsj.com/articles/eve-hewson-on-catfishing-strangers-and-her-new-starring-roles-11614260262", "scraped_at": "2024-10-24 20:25:31", "scanned_status": 0}, {"headline": "Budweiser Brewer Faces an Ill-Timed Hangover", "article_time": "8:22 AM ET", "year": 2021, "month": 2, "day": 25, "keyword": "Heard on the Street", "link": "https://www.wsj.com/articles/budweiser-brewer-faces-an-ill-timed-hangover-11614259375", "scraped_at": "2024-10-24 20:25:31", "scanned_status": 0}, {"headline": "Tiger Woods and the Long Way Back", "article_time": "7:56 AM ET", "year": 2021, "month": 2, "day": 25, "keyword": "Jason Gay", "link": "https://www.wsj.com/articles/tiger-woods-car-accident-golf-comeback-11614256877", "scraped_at": "2024-10-24 20:25:31", "scanned_status": 0}, {"headline": "Lessons From the U.K. About a More-Contagious Covid-19 Variant", "article_time": "7:52 AM ET", "year": 2021, "month": 2, "day": 25, "keyword": "World", "link": "https://www.wsj.com/articles/lessons-from-the-u-k-about-a-more-contagious-covid-19-variant-11614253429", "scraped_at": "2024-10-24 20:25:31", "scanned_status": 0}, {"headline": "Vanguard Charts a Narrow Path in China, Staking Its Future on a Fledgling Venture ", "article_time": "7:51 AM ET", "year": 2021, "month": 2, "day": 25, "keyword": "Markets", "link": "https://www.wsj.com/articles/vanguard-charts-a-narrow-path-in-china-staking-its-future-on-a-fledgling-venture-11614257509", "scraped_at": "2024-10-24 20:25:31", "scanned_status": 0}, {"headline": "Hard Seltzers Help Bud Brewer Regain Some Sparkle ", "article_time": "7:39 AM ET", "year": 2021, "month": 2, "day": 25, "keyword": "Business", "link": "https://www.wsj.com/articles/hard-seltzers-help-bud-brewer-regain-some-sparkle-11614252810", "scraped_at": "2024-10-24 20:25:31", "scanned_status": 0}, {"headline": "\u2018Fortnite\u2019 Creator, Apple Fight Reels in More Tech Players", "article_time": "7:14 AM ET", "year": 2021, "month": 2, "day": 25, "keyword": "Tech", "link": "https://www.wsj.com/articles/fight-between-fortnite-creator-and-apple-reels-in-more-tech-players-11614254404", "scraped_at": "2024-10-24 20:25:31", "scanned_status": 0}, {"headline": "Restaurant Stocks Are Overfed", "article_time": "7:03 AM ET", "year": 2021, "month": 2, "day": 25, "keyword": "Heard on the Street", "link": "https://www.wsj.com/articles/restaurant-stocks-are-overfed-11614254580", "scraped_at": "2024-10-24 20:25:31", "scanned_status": 0}, {"headline": "What Biden\u2019s Minimum-Wage Plan Means for Restaurant Workers ", "article_time": "7:00 AM ET", "year": 2021, "month": 2, "day": 25, "keyword": "Politics", "link": "https://www.wsj.com/articles/what-president-bidens-minimum-wage-plan-means-for-restaurant-workers-11614254401", "scraped_at": "2024-10-24 20:25:31", "scanned_status": 0}, {"headline": "Dungeons & Dragons Gets a Bigger Role at Hasbro", "article_time": "7:00 AM ET", "year": 2021, "month": 2, "day": 25, "keyword": "N/A", "link": "https://www.wsj.com/articles/dungeons-dragons-gets-a-bigger-role-at-hasbro-11614254403", "scraped_at": "2024-10-24 20:25:31", "scanned_status": 0}, {"headline": "Facebook, WhatsApp and Twitter Face New Rules in India", "article_time": "6:39 AM ET", "year": 2021, "month": 2, "day": 25, "keyword": "Tech", "link": "https://www.wsj.com/articles/facebook-whatsapp-and-twitter-face-new-rules-in-india-11614250424", "scraped_at": "2024-10-24 20:25:31", "scanned_status": 0}, {"headline": "Geely and Volvo Decide to Remain Friends With Benefits ", "article_time": "6:38 AM ET", "year": 2021, "month": 2, "day": 25, "keyword": "Heard on the Street", "link": "https://www.wsj.com/articles/geely-and-volvo-decide-to-remain-friends-with-benefits-11614253124", "scraped_at": "2024-10-24 20:25:31", "scanned_status": 0}, {"headline": "Global Trade Roars Back From Depths of Pandemic", "article_time": "6:37 AM ET", "year": 2021, "month": 2, "day": 25, "keyword": "Economy", "link": "https://www.wsj.com/articles/global-trade-roars-back-from-depths-of-covid-19-pandemic-11614253037", "scraped_at": "2024-10-24 20:25:31", "scanned_status": 0}, {"headline": "Nvidia\u2019s Story Has Gotten Complicated", "article_time": "6:30 AM ET", "year": 2021, "month": 2, "day": 25, "keyword": "Heard on the Street", "link": "https://www.wsj.com/articles/nvidias-story-has-gotten-complicated-11614252605", "scraped_at": "2024-10-24 20:25:31", "scanned_status": 0}, {"headline": "Rich Countries Borrowed $18 Trillion in 2020. Few Seem Worried About Them Paying It Off. ", "article_time": "6:17 AM ET", "year": 2021, "month": 2, "day": 25, "keyword": "Economy", "link": "https://www.wsj.com/articles/rich-countries-borrowed-18-trillion-in-2020-few-seem-worried-about-paying-it-off-11614251857", "scraped_at": "2024-10-24 20:25:31", "scanned_status": 0}, {"headline": "Bank Stocks Are Enjoying the Rate Party, Maybe a Little Too Much ", "article_time": "6:03 AM ET", "year": 2021, "month": 2, "day": 25, "keyword": "Heard on the Street", "link": "https://www.wsj.com/articles/bank-stocks-are-enjoying-the-rate-party-maybe-a-little-too-much-11614250980", "scraped_at": "2024-10-24 20:25:31", "scanned_status": 0}, {"headline": "Squeezed by China, Australian Farmers Cultivate New Markets", "article_time": "5:30 AM ET", "year": 2021, "month": 2, "day": 25, "keyword": "World", "link": "https://www.wsj.com/articles/squeezed-by-chinas-tariffs-australian-farmers-cultivate-new-markets-11614249003", "scraped_at": "2024-10-24 20:25:31", "scanned_status": 0}, {"headline": "Rare Bond-Market Inversion Signals Short-Lived Boost to Inflation ", "article_time": "5:30 AM ET", "year": 2021, "month": 2, "day": 25, "keyword": "Markets", "link": "https://www.wsj.com/articles/rare-bond-market-inversion-signals-short-lived-boost-to-inflation-11614249002", "scraped_at": "2024-10-24 20:25:31", "scanned_status": 0}, {"headline": "GameStop Shares Soar in Last Hour of Trading", "article_time": "5:26 AM ET", "year": 2021, "month": 2, "day": 25, "keyword": "Markets", "link": "https://www.wsj.com/articles/gamestop-shares-more-than-double-in-last-hour-of-trading-11614204788", "scraped_at": "2024-10-24 20:25:31", "scanned_status": 0}, {"headline": "Netflix Wants You to Binge Watch More Korean Dramas ", "article_time": "4:29 AM ET", "year": 2021, "month": 2, "day": 25, "keyword": "Business", "link": "https://www.wsj.com/articles/netflix-wants-you-to-binge-watch-more-korean-dramas-11614239854", "scraped_at": "2024-10-24 20:25:31", "scanned_status": 0}, {"headline": "U.S. Closes Hong Kong Property Sale After Beijing\u2019s Approval", "article_time": "3:20 AM ET", "year": 2021, "month": 2, "day": 25, "keyword": "Real Estate", "link": "https://www.wsj.com/articles/u-s-closes-hong-kong-property-sale-after-beijings-approval-11614241246", "scraped_at": "2024-10-24 20:25:31", "scanned_status": 0}, {"headline": "Autonomous Trucking Startup TuSimple Plans to Go Public in March ", "article_time": "12:50 AM ET", "year": 2021, "month": 2, "day": 25, "keyword": "N/A", "link": "https://www.wsj.com/articles/autonomous-trucking-startup-tusimple-plans-to-go-public-in-march-11614230411", "scraped_at": "2024-10-24 20:25:31", "scanned_status": 0}, {"headline": "Pepper...and Salt", "article_time": "12:01 AM ET", "year": 2021, "month": 2, "day": 25, "keyword": "Pepper & Salt", "link": "https://www.wsj.com/articles/pepper-and-salt-11614200067", "scraped_at": "2024-10-24 20:25:31", "scanned_status": 0}, {"headline": "Ad Campaigns Aim to Counter Covid-19 Vaccine Hesitancy", "article_time": "12:01 AM ET", "year": 2021, "month": 2, "day": 25, "keyword": "CMO Today", "link": "https://www.wsj.com/articles/ad-campaigns-aim-to-counter-covid-19-vaccine-hesitancy-11614229261", "scraped_at": "2024-10-24 20:25:31", "scanned_status": 0}, {"headline": "Biden Rescinds Trump Immigration Restrictions ", "article_time": "10:26 PM ET", "year": 2021, "month": 2, "day": 25, "keyword": "Politics", "link": "https://www.wsj.com/articles/biden-rescinds-trump-immigration-restrictions-11614217531", "scraped_at": "2024-10-24 20:25:31", "scanned_status": 0}, {"headline": "Amazon Faces Questions Over Removal of Book by Conservative Author ", "article_time": "10:22 PM ET", "year": 2021, "month": 2, "day": 25, "keyword": "Media & Marketing", "link": "https://www.wsj.com/articles/republican-senators-send-letter-to-jeff-bezos-asking-why-amazon-pulled-book-by-conservative-author-11614212331", "scraped_at": "2024-10-24 20:25:31", "scanned_status": 0}, {"headline": "WeWork Co-Founder to Get Extra $50 Million", "article_time": "10:13 PM ET", "year": 2021, "month": 2, "day": 25, "keyword": "N/A", "link": "https://www.wsj.com/articles/weworks-adam-neumann-to-get-extra-50-million-payout-in-softbank-settlement-11614220906", "scraped_at": "2024-10-24 20:25:31", "scanned_status": 0}, {"headline": "Paul Ryan to Join Solamere Capital", "article_time": "8:53 PM ET", "year": 2021, "month": 2, "day": 25, "keyword": "N/A", "link": "https://www.wsj.com/articles/paul-ryan-says-he-is-joining-solamere-capital-11614207652", "scraped_at": "2024-10-24 20:25:31", "scanned_status": 0}, {"headline": "Boeing-FAA Ties Still Flawed After 737 MAX Reforms ", "article_time": "8:29 PM ET", "year": 2021, "month": 2, "day": 25, "keyword": "U.S.", "link": "https://www.wsj.com/articles/boeing-faa-ties-still-flawed-after-737-max-reforms-11614216569", "scraped_at": "2024-10-24 20:25:31", "scanned_status": 0}, {"headline": "SEC Opens Review of Corporate Climate Change Disclosures ", "article_time": "8:18 PM ET", "year": 2021, "month": 2, "day": 25, "keyword": "Risk & Compliance Journal", "link": "https://www.wsj.com/articles/sec-opens-review-of-corporate-climate-change-disclosures-11614215912", "scraped_at": "2024-10-24 20:25:31", "scanned_status": 0}, {"headline": "GameStop CFO Was Forced Out as Activist Investor Pushes New Strategy ", "article_time": "7:59 PM ET", "year": 2021, "month": 2, "day": 25, "keyword": "CFO Journal", "link": "https://www.wsj.com/articles/gamestop-cfo-was-forced-out-as-activist-investor-pushes-new-strategy-11614214793", "scraped_at": "2024-10-24 20:25:31", "scanned_status": 0}, {"headline": "Icon to Buy Clinical-Trial Rival PRA in $12 Billion Deal ", "article_time": "7:55 PM ET", "year": 2021, "month": 2, "day": 25, "keyword": "Business", "link": "https://www.wsj.com/articles/icon-to-buy-pra-health-sciences-in-12-billion-deal-11614190274", "scraped_at": "2024-10-24 20:25:31", "scanned_status": 0}, {"headline": "ViacomCBS Shortens Theatrical Window for Paramount+", "article_time": "7:52 PM ET", "year": 2021, "month": 2, "day": 25, "keyword": "Media & Marketing", "link": "https://www.wsj.com/articles/viacomcbs-shortens-theatrical-window-for-paramount-streaming-service-11614205163", "scraped_at": "2024-10-24 20:25:31", "scanned_status": 0}, {"headline": "Markets Suggest the Economy Is Booming But the Recovery Has a Long Way to Go", "article_time": "7:39 PM ET", "year": 2021, "month": 2, "day": 25, "keyword": "Markets", "link": "https://www.wsj.com/articles/markets-suggest-the-economy-is-booming-the-recovery-has-a-long-way-to-go-though-11614213582", "scraped_at": "2024-10-24 20:25:31", "scanned_status": 0}, {"headline": "Moderna Says New Variant Vaccine Is Ready for Human Testing", "article_time": "7:18 PM ET", "year": 2021, "month": 2, "day": 25, "keyword": "Health", "link": "https://www.wsj.com/articles/moderna-says-covid-19-vaccine-for-south-africa-strain-is-ready-for-human-testing-11614201000", "scraped_at": "2024-10-24 20:25:31", "scanned_status": 0}, {"headline": "Manhattan Donors Pour Cash Into New York City Mayoral Race", "article_time": "7:02 PM ET", "year": 2021, "month": 2, "day": 25, "keyword": "Politics", "link": "https://www.wsj.com/articles/manhattan-donors-pour-cash-into-new-york-city-mayoral-race-11614211366", "scraped_at": "2024-10-24 20:25:31", "scanned_status": 0}, {"headline": "Facebook, Google Face \u2018Strong Pipeline\u2019 of Privacy Rulings in Europe ", "article_time": "7:00 PM ET", "year": 2021, "month": 2, "day": 25, "keyword": "Tech", "link": "https://www.wsj.com/articles/facebook-google-face-strong-pipeline-of-privacy-rulings-in-europe-11614211200", "scraped_at": "2024-10-24 20:25:31", "scanned_status": 0}, {"headline": "Biden Announces Three Nominees for Postal Service Board ", "article_time": "7:00 PM ET", "year": 2021, "month": 2, "day": 25, "keyword": "Politics", "link": "https://www.wsj.com/articles/biden-announces-three-nominees-for-postal-service-board-of-governors-11614202943", "scraped_at": "2024-10-24 20:25:31", "scanned_status": 0}]