[{"headline": "Jury Orders Trump to Pay E. Jean Carroll $83 Million for Defamation", "article_time": "6:56 PM ET", "year": 2024, "month": 1, "day": 26, "keyword": "U.S.", "link": "https://www.wsj.com/us-news/law/jury-set-to-decide-whether-trump-must-pay-e-jean-carroll-again-for-defamation-07785bd5", "scraped_at": "2024-10-26 22:13:46", "scanned_status": 0}, {"headline": "Hawaii\u2019s Electric Utility Could Soon Feel the Burn", "article_time": "6:17 PM ET", "year": 2024, "month": 1, "day": 26, "keyword": "Cross Country", "link": "https://www.wsj.com/articles/hawaiis-electric-utility-could-soon-feel-the-burn-lahaina-wildfire-bc79b9b7", "scraped_at": "2024-10-26 22:13:46", "scanned_status": 0}, {"headline": "Notable & Quotable: History", "article_time": "6:16 PM ET", "year": 2024, "month": 1, "day": 26, "keyword": "Notable & Quotable", "link": "https://www.wsj.com/articles/notable-quotable-history-woke-columbus-president-colonialism-slavery-936e130d", "scraped_at": "2024-10-26 22:13:46", "scanned_status": 0}, {"headline": "The Score: Netflix, United Airlines, Tesla and More Stocks That Defined the Week", "article_time": "6:09 PM ET", "year": 2024, "month": 1, "day": 26, "keyword": "Markets", "link": "https://www.wsj.com/finance/stocks/the-score-netflix-united-airlines-tesla-and-more-stocks-that-defined-the-week-8b399cd9", "scraped_at": "2024-10-26 22:13:46", "scanned_status": 0}, {"headline": "Biden\u2019s LNG \u2018Pause\u2019 Will Hurt the Environment", "article_time": "6:02 PM ET", "year": 2024, "month": 1, "day": 26, "keyword": "Commentary", "link": "https://www.wsj.com/articles/bidens-lng-export-permit-pause-will-hurt-the-environment-and-carry-geopolitical-risk-76dbcc99", "scraped_at": "2024-10-26 22:13:46", "scanned_status": 0}, {"headline": "How Climate Policy Went Wrong", "article_time": "6:01 PM ET", "year": 2024, "month": 1, "day": 26, "keyword": "Business World", "link": "https://www.wsj.com/articles/how-climate-policy-went-wrong-new-aerosal-study-energy-subsidies-carbon-tax-4e437371", "scraped_at": "2024-10-26 22:13:46", "scanned_status": 0}, {"headline": "Can Readers Save the New York Times?", "article_time": "6:00 PM ET", "year": 2024, "month": 1, "day": 26, "keyword": "Best of the Web", "link": "https://www.wsj.com/articles/can-readers-save-the-new-york-times-6ce799f1", "scraped_at": "2024-10-26 22:13:46", "scanned_status": 0}, {"headline": "Biden and the TikTok Anti-LNG Crusade", "article_time": "5:52 PM ET", "year": 2024, "month": 1, "day": 26, "keyword": "Review & Outlook", "link": "https://www.wsj.com/articles/biden-lng-export-pause-white-house-tiktok-climate-bill-mckibben-3efb5287", "scraped_at": "2024-10-26 22:13:46", "scanned_status": 0}, {"headline": "The U.N.\u2019s War on Israel", "article_time": "5:51 PM ET", "year": 2024, "month": 1, "day": 26, "keyword": "Review & Outlook", "link": "https://www.wsj.com/articles/united-nations-unrwa-israel-hamas-gaza-international-court-of-justice-south-africa-a806157a", "scraped_at": "2024-10-26 22:13:46", "scanned_status": 0}, {"headline": "Who\u2019s Radical on Abortion Now?", "article_time": "5:51 PM ET", "year": 2024, "month": 1, "day": 26, "keyword": "Review & Outlook", "link": "https://www.wsj.com/articles/wisconsin-abortion-bill-tony-evers-veto-9e5949c0", "scraped_at": "2024-10-26 22:13:46", "scanned_status": 0}, {"headline": "Teachers Unions Against Teacher Pay", "article_time": "5:49 PM ET", "year": 2024, "month": 1, "day": 26, "keyword": "Review & Outlook", "link": "https://www.wsj.com/articles/arizona-teacher-pay-katie-hobbs-teachers-union-0531e0d3", "scraped_at": "2024-10-26 22:13:46", "scanned_status": 0}, {"headline": "Texas Bans Barclays From Bond Market Due to Bank\u2019s ESG Policies", "article_time": "4:55 PM ET", "year": 2024, "month": 1, "day": 26, "keyword": "Finance", "link": "https://www.wsj.com/politics/policy/texas-bans-barclays-from-participating-in-bond-market-due-to-esg-commitments-fb4d3893", "scraped_at": "2024-10-26 22:13:46", "scanned_status": 0}, {"headline": "This Year, Tesla Stock Isn\u2019t So Magnificent", "article_time": "4:45 PM ET", "year": 2024, "month": 1, "day": 26, "keyword": "Stocks", "link": "https://www.wsj.com/finance/stocks/stocks-magnificent-seven-tesla-ea645bc0", "scraped_at": "2024-10-26 22:13:46", "scanned_status": 0}, {"headline": "Flexport Plans to Cut Another\u00a020% of Staff\u00a0", "article_time": "4:41 PM ET", "year": 2024, "month": 1, "day": 26, "keyword": "N/A", "link": "https://www.wsj.com/articles/flexport-plans-to-cut-another20-of-staff-c4c3be60", "scraped_at": "2024-10-26 22:13:46", "scanned_status": 0}, {"headline": "\u2018Vanessa\u2019: Samuel Barber\u2019s Riveting Romantic Opera", "article_time": "4:36 PM ET", "year": 2024, "month": 1, "day": 26, "keyword": "Masterpiece", "link": "https://www.wsj.com/arts-culture/music/vanessa-samuel-barbers-riveting-romantic-opera-23ec0dda", "scraped_at": "2024-10-26 22:13:46", "scanned_status": 0}, {"headline": "Canadian Cardinal Accused of Sexual Assault", "article_time": "4:26 PM ET", "year": 2024, "month": 1, "day": 26, "keyword": "Canada", "link": "https://www.wsj.com/world/canadian-cardinal-accused-of-sexual-assault-e5cd3cc1", "scraped_at": "2024-10-26 22:13:46", "scanned_status": 0}, {"headline": "Andrew Cuomo Sexually Harassed State Employees, Justice Department Says", "article_time": "4:26 PM ET", "year": 2024, "month": 1, "day": 26, "keyword": "Politics", "link": "https://www.wsj.com/politics/policy/andrew-cuomo-sexually-harassed-state-employees-justice-department-says-8a404290", "scraped_at": "2024-10-26 22:13:46", "scanned_status": 0}, {"headline": "Stocks Notch Weekly Gains; Major Indexes Sit Near Records", "article_time": "4:17 PM ET", "year": 2024, "month": 1, "day": 26, "keyword": "U.S. Markets", "link": "https://www.wsj.com/finance/stocks/global-stocks-markets-dow-news-01-26-2024-05099cf8", "scraped_at": "2024-10-26 22:13:46", "scanned_status": 0}, {"headline": "The Journal Acrostic (Saturday Variety Puzzle, January 27)", "article_time": "4:02 PM ET", "year": 2024, "month": 1, "day": 26, "keyword": "Variety Puzzle", "link": "https://www.wsj.com/articles/the-journal-acrostic-saturday-variety-puzzle-january-27-48a93053", "scraped_at": "2024-10-26 22:13:46", "scanned_status": 0}, {"headline": "Providing Context (Saturday Crossword, January 27)", "article_time": "4:01 PM ET", "year": 2024, "month": 1, "day": 26, "keyword": "Crossword", "link": "https://www.wsj.com/articles/providing-context-saturday-crossword-january-27-c8bb50a8", "scraped_at": "2024-10-26 22:13:46", "scanned_status": 0}, {"headline": "16 Books We Read This Week", "article_time": "3:49 PM ET", "year": 2024, "month": 1, "day": 26, "keyword": "Bookshelf", "link": "https://www.wsj.com/arts-culture/books/16-books-we-read-this-week-1638b38b", "scraped_at": "2024-10-26 22:13:46", "scanned_status": 0}, {"headline": "What\u2019s Next in Menswear? 6 Standout Trends From the Latest Runway Shows", "article_time": "3:48 PM ET", "year": 2024, "month": 1, "day": 26, "keyword": "Fashion", "link": "https://www.wsj.com/style/fashion/whats-next-in-menswear-standout-trends-mens-fashion-week-fall-winter-2024-9bf84f9d", "scraped_at": "2024-10-26 22:13:46", "scanned_status": 0}, {"headline": "Nutritionist With Roster of A-List Clients Asks $26.7 Million for West London Home", "article_time": "3:45 PM ET", "year": 2024, "month": 1, "day": 26, "keyword": "market makers", "link": "https://www.wsj.com/real-estate/luxury-homes/nutritionist-with-roster-of-a-list-clients-asks-26-7-million-for-west-london-home-641d360d", "scraped_at": "2024-10-26 22:13:46", "scanned_status": 0}, {"headline": "World Court Rejects Demand for Gaza Cease-Fire", "article_time": "3:44 PM ET", "year": 2024, "month": 1, "day": 26, "keyword": "World", "link": "https://www.wsj.com/world/middle-east/world-court-rejects-demand-for-gaza-cease-fire-896312cb", "scraped_at": "2024-10-26 22:13:46", "scanned_status": 0}, {"headline": "Kenya\u2019s High Court Bars U.N.-Backed Mission to Send Kenyan Police to Haiti", "article_time": "3:31 PM ET", "year": 2024, "month": 1, "day": 26, "keyword": "World", "link": "https://www.wsj.com/world/americas/kenyas-high-court-bars-u-n-backed-mission-to-send-kenyan-police-to-haiti-eb54e865", "scraped_at": "2024-10-26 22:13:46", "scanned_status": 0}, {"headline": "\u2018Joan Snyder: ComeClose\u2019 Review: Reinvention Repurposed", "article_time": "3:27 PM ET", "year": 2024, "month": 1, "day": 26, "keyword": "Art Review", "link": "https://www.wsj.com/arts-culture/fine-art/joan-snyder-comeclose-review-reinvention-repurposed-airdigital-4ba8e667", "scraped_at": "2024-10-26 22:13:46", "scanned_status": 0}, {"headline": "Biden Aides Fret That Support for Israel Will Hurt Re-Election Prospects", "article_time": "3:09 PM ET", "year": 2024, "month": 1, "day": 26, "keyword": "Election 2024", "link": "https://www.wsj.com/politics/policy/biden-campaign-contends-with-new-challenge-hecklers-from-his-own-side-9b222ca1", "scraped_at": "2024-10-26 22:13:46", "scanned_status": 0}, {"headline": "Arts Calendar: Happenings for the Week of January 28", "article_time": "3:07 PM ET", "year": 2024, "month": 1, "day": 26, "keyword": "Arts Calendar", "link": "https://www.wsj.com/arts-culture/television/arts-calendar-happenings-for-the-week-of-january-28-airdigital-6d98b56e", "scraped_at": "2024-10-26 22:13:46", "scanned_status": 0}, {"headline": "U.S. Secretly Alerted Iran Ahead of Islamic State Terror Attack", "article_time": "2:52 PM ET", "year": 2024, "month": 1, "day": 26, "keyword": "N/A", "link": "https://www.wsj.com/world/middle-east/u-s-secretly-alerted-iran-ahead-of-islamic-state-terrorist-attack-af77a19a", "scraped_at": "2024-10-26 22:13:46", "scanned_status": 0}, {"headline": "Booz Allen\u2019s Quarterly Net Income Rises Sharply", "article_time": "2:43 PM ET", "year": 2024, "month": 1, "day": 26, "keyword": "Earnings", "link": "https://www.wsj.com/business/earnings/booz-allens-quarterly-net-income-rises-sharply-78c394d5", "scraped_at": "2024-10-26 22:13:46", "scanned_status": 0}, {"headline": "\u2018Ashoka\u2019 Review: Conquer First, Enlighten Later", "article_time": "2:31 PM ET", "year": 2024, "month": 1, "day": 26, "keyword": "Bookshelf", "link": "https://www.wsj.com/arts-culture/books/ashoka-review-conquer-first-enlighten-later-1f3a229f", "scraped_at": "2024-10-26 22:13:46", "scanned_status": 0}, {"headline": "Qatar, an American Ally? Think Again", "article_time": "2:27 PM ET", "year": 2024, "month": 1, "day": 26, "keyword": "Letters", "link": "https://www.wsj.com/articles/qatar-no-us-ally-al-udeid-jazeera-terrorism-af512a70", "scraped_at": "2024-10-26 22:13:46", "scanned_status": 0}, {"headline": "Donald Trump, His Enemies and His Voters", "article_time": "2:26 PM ET", "year": 2024, "month": 1, "day": 26, "keyword": "Letters", "link": "https://www.wsj.com/articles/donald-trump-2024-election-voters-565f2c12", "scraped_at": "2024-10-26 22:13:46", "scanned_status": 0}, {"headline": "Thank You for All the Lunches", "article_time": "2:25 PM ET", "year": 2024, "month": 1, "day": 26, "keyword": "Letters", "link": "https://www.wsj.com/articles/jason-gay-pack-school-lunch-mom-dad-aaffc978", "scraped_at": "2024-10-26 22:13:46", "scanned_status": 0}, {"headline": "Macron Scratches an Itch to Disfigure Notre-Dame", "article_time": "2:25 PM ET", "year": 2024, "month": 1, "day": 26, "keyword": "Letters", "link": "https://www.wsj.com/articles/notre-dame-cathedral-france-macron-f2da049a", "scraped_at": "2024-10-26 22:13:46", "scanned_status": 0}, {"headline": "Two Questions for Republican Voters", "article_time": "2:24 PM ET", "year": 2024, "month": 1, "day": 26, "keyword": "Letters", "link": "https://www.wsj.com/articles/trump-bidne-haley-republican-president-2024-e2addd46", "scraped_at": "2024-10-26 22:13:46", "scanned_status": 0}, {"headline": "Which Presidential Candidate Is Which?", "article_time": "2:23 PM ET", "year": 2024, "month": 1, "day": 26, "keyword": "Letters", "link": "https://www.wsj.com/articles/trump-biden-age-honesty-election-2024-3ce38688", "scraped_at": "2024-10-26 22:13:46", "scanned_status": 0}, {"headline": "Help! Is It Possible to Have a Soaking Tub That\u2019s Both Chic and Safe?", "article_time": "2:15 PM ET", "year": 2024, "month": 1, "day": 26, "keyword": "Design", "link": "https://www.wsj.com/style/design/soaking-tub-safe-and-stylish-d9a4d990", "scraped_at": "2024-10-26 22:13:46", "scanned_status": 0}, {"headline": "The Modular Method of Mahjong", "article_time": "2:00 PM ET", "year": 2024, "month": 1, "day": 26, "keyword": "Everyday Math", "link": "https://www.wsj.com/science/the-modular-method-of-mahjong-9135fbeb", "scraped_at": "2024-10-26 22:13:46", "scanned_status": 0}, {"headline": "Follow the Left\u2019s Example to Reform Higher Ed", "article_time": "1:52 PM ET", "year": 2024, "month": 1, "day": 26, "keyword": "Commentary", "link": "https://www.wsj.com/articles/follow-the-lefts-example-to-reform-higher-ed-3c94d9b9", "scraped_at": "2024-10-26 22:13:46", "scanned_status": 0}, {"headline": "\u2018Soap Opera\u2019: How a Sudsy Label Got Attached to a Frothy TV Genre", "article_time": "1:40 PM ET", "year": 2024, "month": 1, "day": 26, "keyword": "Word on the Street", "link": "https://www.wsj.com/arts-culture/television/soap-opera-how-a-sudsy-label-got-attached-to-a-frothy-tv-genre-25716977", "scraped_at": "2024-10-26 22:13:46", "scanned_status": 0}, {"headline": "U.S. Halts Funding for U.N. Agency Amid Claims Staff Took Part in Oct. 7 Attacks", "article_time": "1:31 PM ET", "year": 2024, "month": 1, "day": 26, "keyword": "Middle East", "link": "https://www.wsj.com/world/middle-east/u-s-halts-funding-for-u-n-agency-amid-claims-staff-took-part-in-oct-7-attacks-3247918b", "scraped_at": "2024-10-26 22:13:46", "scanned_status": 0}, {"headline": "Cooler Inflation Keeps Door Open for Rate Cuts This Year", "article_time": "1:15 PM ET", "year": 2024, "month": 1, "day": 26, "keyword": "U.S. Economy", "link": "https://www.wsj.com/economy/central-banking/what-to-watch-in-fridays-spending-report-a-last-look-at-inflation-before-the-fed-meeting-353665d9", "scraped_at": "2024-10-26 22:13:46", "scanned_status": 0}, {"headline": "\u2018Yesterday\u2019 and \u2018Foreverism\u2019 Review: Forward Into the Past", "article_time": "1:08 PM ET", "year": 2024, "month": 1, "day": 26, "keyword": "Bookshelf", "link": "https://www.wsj.com/arts-culture/books/yesterday-and-foreverism-review-forward-into-the-past-450003ff", "scraped_at": "2024-10-26 22:13:46", "scanned_status": 0}, {"headline": "When Consumers Prefer Simple Packaging\u2014and When They Don\u2019t", "article_time": "1:00 PM ET", "year": 2024, "month": 1, "day": 26, "keyword": "Journal Reports: Leadership", "link": "https://www.wsj.com/business/retail/consumers-simple-packaging-5f49f46e", "scraped_at": "2024-10-26 22:13:46", "scanned_status": 0}, {"headline": "Russell Hamler, Last Surviving Member of a World War II \u2018Marauders\u2019 Unit, Dies at 99", "article_time": "1:00 PM ET", "year": 2024, "month": 1, "day": 26, "keyword": "Obituaries", "link": "https://www.wsj.com/us-news/russell-hamler-world-war-ii-marauders-unit-dies-at-99-3ba7ff5b", "scraped_at": "2024-10-26 22:13:46", "scanned_status": 0}, {"headline": "Today\u2019s Most Seductive Styles Don\u2019t Show Skin", "article_time": "12:30 PM ET", "year": 2024, "month": 1, "day": 26, "keyword": "Fashion", "link": "https://www.wsj.com/style/fashion/modest-dressing-todays-most-seductive-styles-dont-show-skin-c0bfe8d1", "scraped_at": "2024-10-26 22:13:46", "scanned_status": 0}, {"headline": "Alabama Inmate Is First in U.S. to Be Executed by Nitrogen Gas", "article_time": "12:27 PM ET", "year": 2024, "month": 1, "day": 26, "keyword": "U.S.", "link": "https://www.wsj.com/us-news/law/alabama-inmate-kenneth-eugene-smith-execution-nitrogen-hypoxia-b2623881", "scraped_at": "2024-10-26 22:13:46", "scanned_status": 0}, {"headline": "Biden Pauses Approvals for LNG Exports", "article_time": "12:22 PM ET", "year": 2024, "month": 1, "day": 26, "keyword": "Politics", "link": "https://www.wsj.com/politics/policy/biden-pauses-approvals-for-lng-exports-3d065745", "scraped_at": "2024-10-26 22:13:46", "scanned_status": 0}, {"headline": "\u2018The Holocaust\u2019 Review: The Road to Genocide", "article_time": "12:00 PM ET", "year": 2024, "month": 1, "day": 26, "keyword": "Bookshelf", "link": "https://www.wsj.com/arts-culture/books/the-holocaust-review-the-road-to-genocide-fe81b75a", "scraped_at": "2024-10-26 22:13:46", "scanned_status": 0}]